compas_pythreejs/__init__.py
compas_pythreejs/__main__.py
compas_pythreejs/display.py
compas_pythreejs/conversions/__init__.py
compas_pythreejs/conversions/colors.py
compas_pythreejs/conversions/geometry.py
compas_pythreejs/scene/__init__.py
compas_pythreejs/scene/boxobject.py
compas_pythreejs/scene/coneobject.py
compas_pythreejs/scene/cylinderobject.py
compas_pythreejs/scene/meshobject.py
compas_pythreejs/scene/polyhedronobject.py
compas_pythreejs/scene/sceneobject.py
compas_pythreejs/scene/sphereobject.py
compas_pythreejs/scene/torusobject.py
compas_pythreejs-0.2.4.dist-info/AUTHORS.md
compas_pythreejs-0.2.4.dist-info/LICENSE
compas_pythreejs-0.2.4.dist-info/METADATA
compas_pythreejs-0.2.4.dist-info/WHEEL
compas_pythreejs-0.2.4.dist-info/top_level.txt
compas_pythreejs-0.2.4.dist-info/RECORD
