Metadata-Version: 2.1
Name: compas-pythreejs
Version: 0.2.4
Summary: Notebook visualization backend for COMPAS using pythreejs
Home-page: https://github.com/compas-dev/compas_pythreejs
Author: tom van mele
Author-email: tom.v.mele@gmail.com
License: MIT license
Classifier: Development Status :: 4 - Beta
Classifier: Intended Audience :: Developers
Classifier: Topic :: Scientific/Engineering
Classifier: License :: OSI Approved :: MIT License
Classifier: Operating System :: Unix
Classifier: Operating System :: POSIX
Classifier: Operating System :: Microsoft :: Windows
Classifier: Programming Language :: Python
Classifier: Programming Language :: Python :: 3
Classifier: Programming Language :: Python :: 3.8
Classifier: Programming Language :: Python :: 3.9
Classifier: Programming Language :: Python :: 3.10
Classifier: Programming Language :: Python :: Implementation :: CPython
Requires-Python: >=3.8
License-File: LICENSE
License-File: AUTHORS.md
Requires-Dist: compas >=2.0.0b3
Requires-Dist: pythreejs
